llm_mcp_score/__init__.py
llm_mcp_score/server.py
llm_mcp_score-0.1.2.dist-info/METADATA
llm_mcp_score-0.1.2.dist-info/WHEEL
llm_mcp_score-0.1.2.dist-info/entry_points.txt
llm_mcp_score-0.1.2.dist-info/top_level.txt
llm_mcp_score-0.1.2.dist-info/RECORD
