Metadata-Version: 2.4
Name: llm_mcp_score
Version: 0.1.2
Summary: A minimal MCP service for testing LLM understanding and invocation of MCP tools
Project-URL: Homepage, https://github.com/yourusername/llm_mcp_score
Requires-Python: >=3.8
Requires-Dist: mcp[server]>=1.2.0
